custom_ls/__init__.py
custom_ls/custom_ls.py
custom_ls-0.0.1.dist-info/METADATA
custom_ls-0.0.1.dist-info/WHEEL
custom_ls-0.0.1.dist-info/top_level.txt
custom_ls-0.0.1.dist-info/RECORD
